generic_iterative_stemmer/__init__.py
generic_iterative_stemmer/errors.py
generic_iterative_stemmer/helpers.py
generic_iterative_stemmer/models/__init__.py
generic_iterative_stemmer/models/stemmed_keyed_vectors.py
generic_iterative_stemmer/training/__init__.py
generic_iterative_stemmer/training/base/__init__.py
generic_iterative_stemmer/training/base/create_corpus.py
generic_iterative_stemmer/training/base/fast_text.py
generic_iterative_stemmer/training/base/word2vec.py
generic_iterative_stemmer/training/stemming/__init__.py
generic_iterative_stemmer/training/stemming/common_affix_finder.py
generic_iterative_stemmer/training/stemming/corpus_stemmer.py
generic_iterative_stemmer/training/stemming/default_stem_generator.py
generic_iterative_stemmer/training/stemming/fixed_vocabulary_stem_generator.py
generic_iterative_stemmer/training/stemming/ft_stemming_trainer.py
generic_iterative_stemmer/training/stemming/stem_generator.py
generic_iterative_stemmer/training/stemming/stemming_trainer.py
generic_iterative_stemmer/training/stemming/w2v_stemming_trainer.py
generic_iterative_stemmer-1.2.0.dist-info/LICENSE
generic_iterative_stemmer-1.2.0.dist-info/METADATA
generic_iterative_stemmer-1.2.0.dist-info/WHEEL
generic_iterative_stemmer-1.2.0.dist-info/RECORD
