Metadata-Version: 2.1
Name: generic-iterative-stemmer
Version: 1.2.0
Summary: A generic language stemming utility, dedicated for gensim word-embedding.
Author: Asaf Kali
Author-email: asaf.kali@mail.huji.ac.il
Requires-Python: >=3.10,<4.0
Classifier: Programming Language :: Python :: 3
Classifier: Programming Language :: Python :: 3.10
Classifier: Programming Language :: Python :: 3.11
Classifier: Programming Language :: Python :: 3.12
Provides-Extra: training
Requires-Dist: editdistance (>=0.6,<0.7) ; extra == "training"
Requires-Dist: fasttext-wheel (>=0.9.2,<0.10.0) ; extra == "training"
Requires-Dist: gensim (>=4.1,<5.0)
Requires-Dist: matplotlib (>=3.5,<4.0) ; extra == "training"
Requires-Dist: numpy (>=1.21,<2.0) ; extra == "training"
Requires-Dist: pandas (>=1.3,<2.0) ; extra == "training"
Requires-Dist: pydantic (>=2.0,<3.0)
Requires-Dist: the-spymaster-util[logging] (>=3.2,<4.0) ; extra == "training"
Requires-Dist: tqdm (>=4.62,<5.0) ; extra == "training"
Project-URL: Homepage, https://github.com/asaf-kali/generic-iterative-stemmer
Project-URL: Issues, https://github.com/asaf-kali/generic-iterative-stemmer/issues
Project-URL: Repository, https://github.com/asaf-kali/generic-iterative-stemmer
